{
  "type": "FeatureCollection",
  "features": [
    {
      "type": "Feature",
      "geometry": {
        "type": "Point",
        "coordinates": [114.106337, 22.544621]
      },
      "properties": {
        "marker-symbol": "shop",
        "name": "kkmall",
        "zipcode": 518001
      }
    },
    {
      "type": "Feature",
      "geometry": {
        "type": "Point",
        "coordinates": [113.991296, 22.524182]
      },
      "properties": {
        "marker-symbol": "shop",
        "name": "欢乐海岸",
        "zipcode": 518053
      }
    },
    {
      "type": "Feature",
      "geometry": {
        "type": "Point",
        "coordinates": [114.053704, 22.534182]
      },
      "properties": {
        "marker-symbol": "shop",
        "name": "星河 COCOPARK",
        "zipcode": 518026
      }
    }
  ]
}
