{"type":"FeatureCollection","features":[{"type":"Feature","properties":{"marker-symbol":"shop","name":"kkmall","zipcode":518001},"geometry":{"type":"Point","coordinates":[114.106337,22.544621]}},{"type":"Feature","properties":{"marker-symbol":"shop","name":"欢乐海岸","zipcode":518053},"geometry":{"type":"Point","coordinates":[113.991296,22.524182]}},{"type":"Feature","properties":{"marker-symbol":"shop","name":"星河 COCOPARK","zipcode":518026},"geometry":{"type":"Point","coordinates":[114.053704,22.534182]}}]}